asmat/__init__.py
asmat/__main__.py
asmat/assembly_parser.py
asmat/atp.py
asmat/compiler.py
asmat/const.py
asmat/dependencies.py
asmat/generation.py
asmat/instructions.py
asmat/option.py
asmat/reader.py
asmat/settings.py
asmat/validation.py
asmat/analysis/analysis_output.py
asmat/analysis/analyze.py
asmat/analysis/data.db
asmat/analysis/editor.py
asmat/analysis/parse_html.py
asmat-1.2.1.dist-info/LICENSE.md
asmat-1.2.1.dist-info/METADATA
asmat-1.2.1.dist-info/WHEEL
asmat-1.2.1.dist-info/top_level.txt
asmat-1.2.1.dist-info/RECORD
