Metadata-Version: 2.1
Name: asmat
Version: 1.2.1
Summary: Assembly Testing and Analysis
Home-page: https://github.com/erwanlem/atp
Download-URL: https://github.com/erwanlem/atp/archive/refs/tags/v1.0.tar.gz
Author: Erwan LEMATTRE
Author-email: erwanlem4@gmail.com
License: MIT
Keywords: ASSEMBLER,TEST,ANALYSIS
Classifier: Programming Language :: Python :: 3
Classifier: Development Status :: 3 - Alpha
Classifier: Intended Audience :: Developers
Classifier: Topic :: Software Development :: Build Tools
Classifier: License :: OSI Approved :: MIT License
Classifier: Operating System :: OS Independent
Requires-Python: >=3.6
License-File: LICENSE.md
Requires-Dist: bs4
Requires-Dist: matplotlib
Requires-Dist: pillow
